README.md
license.md
main.py
requirements.txt
setup.py
PyIpify/__init__.py
PyIpify/__main__.py
PyIpify.egg-info/PKG-INFO
PyIpify.egg-info/SOURCES.txt
PyIpify.egg-info/dependency_links.txt
PyIpify.egg-info/requires.txt
PyIpify.egg-info/top_level.txt
PyIpify/asyncronous/__init__.py
PyIpify/asyncronous/find_ipv4.py
PyIpify/asyncronous/find_ipv6.py
PyIpify/asyncronous/__pycache__/__init__.cpython-310.pyc
PyIpify/asyncronous/__pycache__/__init__.cpython-311.pyc
PyIpify/asyncronous/__pycache__/find_ipv4.cpython-310.pyc
PyIpify/asyncronous/__pycache__/find_ipv4.cpython-311.pyc
PyIpify/asyncronous/__pycache__/find_ipv6.cpython-310.pyc
PyIpify/asyncronous/__pycache__/find_ipv6.cpython-311.pyc
PyIpify/syncronous/__init__.py
PyIpify/syncronous/find_ipv4.py
PyIpify/syncronous/find_ipv6.py
PyIpify/syncronous/__pycache__/__init__.cpython-310.pyc
PyIpify/syncronous/__pycache__/__init__.cpython-311.pyc
PyIpify/syncronous/__pycache__/find_ipv4.cpython-310.pyc
PyIpify/syncronous/__pycache__/find_ipv4.cpython-311.pyc
PyIpify/syncronous/__pycache__/find_ipv6.cpython-310.pyc
PyIpify/syncronous/__pycache__/find_ipv6.cpython-311.pyc
Pyipify/__init__.py
Pyipify/__main__.py