Metadata-Version: 2.1
Name: PyIpify
Version: 0.0.3
Summary: A simple python library to find the public ip address of the system.
Home-page: https://github.com/SigireddyBalasai/ipify
Download-URL: https://github.com/SigireddyBalasai/AsyncPywhatKit/archive/refs/tags/1.0.tar.gz
Author: SigireddyBalasai
Author-email: sigireddybalasai@gmail.com
License: MIT
Keywords: ipify,ip,ip address,ipify.org,ipify api,ipify python,ipify python library,ipify python api,ipify python library,ipify python api,ipify python package,ipify,ipify cli,ipify asyncronous,ipify syncronous
Classifier: Development Status :: 5 - Production/Stable
Classifier: Intended Audience :: Developers
Classifier: Topic :: Software Development :: Build Tools
Classifier: License :: OSI Approved :: MIT License
Classifier: Programming Language :: Python :: 3.8
Classifier: Programming Language :: Python :: 3.9
Classifier: Programming Language :: Python :: 3.10
Classifier: Programming Language :: Python :: 3.11
License-File: license.md
